pete/__init__.py
pete/_helpers.py
pete/broadcaster/__init__.py
pete/broadcaster/broadcaster.py
pete/db/__init__.py
pete/db/db.py
pete/examples/__init__.py
pete/examples/example_runner.py
pete/examples/string_broadcaster.py
pete/examples/time_checker.py
pete/petemail/__init__.py
pete/petemail/petemail.py
pete/runner/__init__.py
pete/runner/runner.py
pete/task/__init__.py
pete/task/task.py
pete-0.1.2.dist-info/DESCRIPTION.rst
pete-0.1.2.dist-info/METADATA
pete-0.1.2.dist-info/metadata.json
pete-0.1.2.dist-info/RECORD
pete-0.1.2.dist-info/top_level.txt
pete-0.1.2.dist-info/WHEEL
