Metadata-Version: 2.0
Name: pete
Version: 0.1.2
Summary: A simple taskrunner
Home-page: https://github.com/ColCarroll/pete
Author: Colin Carroll
Author-email: colcarroll@gmail.com
License: MIT
Platform: UNKNOWN
Classifier: Development Status :: 3 - Alpha
Classifier: Intended Audience :: Developers
Classifier: License :: OSI Approved :: MIT License
Classifier: Programming Language :: Python :: 3
Classifier: Programming Language :: Python :: 3.3
Classifier: Programming Language :: Python :: 3.4
Classifier: Programming Language :: Python :: 3.5
Provides-Extra: dev
Requires-Dist: ipython; extra == 'dev'
Requires-Dist: flake8; extra == 'dev'
Provides-Extra: test
Requires-Dist: pytest; extra == 'test'
Requires-Dist: pytest-cov; extra == 'test'
